httpx_folio-0.3.0.dist-info/METADATA
httpx_folio-0.3.0.dist-info/WHEEL
httpx_folio-0.3.0.dist-info/entry_points.txt
httpx_folio/__init__.py
httpx_folio/auth.py
httpx_folio/factories.py
httpx_folio/py.typed
httpx_folio/query.py
httpx_folio-0.3.0.dist-info/RECORD
