Metadata-Version: 2.1
Name: httpx-folio
Version: 0.3.0
Summary: FOLIO related niceties for the next generation HTTP client for Python
Author-Email: Katherine Bargar <kbargar@fivecolleges.edu>
License: Apache-2.0
Project-URL: Homepage, https://github.com/Five-Colleges-Incorporated/httpx-folio
Project-URL: Bug Tracker, https://github.com/Five-Colleges-Incorporated/httpx-folio/issues
Requires-Python: >=3.9
Requires-Dist: httpx>=0.20.0
Requires-Dist: httpx-retries>=0.4.1
